jenkins_fire_cli/__init__.py
jenkins_fire_cli/config.py
jenkins_fire_cli/main.py
jenkins_fire_cli-0.1.1.dist-info/entry_points.txt
jenkins_fire_cli-0.1.1.dist-info/LICENSE
jenkins_fire_cli-0.1.1.dist-info/WHEEL
jenkins_fire_cli-0.1.1.dist-info/METADATA
jenkins_fire_cli-0.1.1.dist-info/RECORD
