Metadata-Version: 2.1
Name: jenkins-fire-cli
Version: 0.1.1
Summary: 
Author: weihong.xu
Author-email: xuweihong.cn@gmail.com
Requires-Python: >=3.8,<4.0
Classifier: Programming Language :: Python :: 3
Classifier: Programming Language :: Python :: 3.8
Classifier: Programming Language :: Python :: 3.9
Classifier: Programming Language :: Python :: 3.10
Requires-Dist: fire (>=0.4.0,<0.5.0)
